README.rst
setup.py
monarch/__init__.py
monarch/local.py
monarch/migrations.py
monarch/models.py
monarch/mongo.py
monarch/query_sets.py
monarch/s3.py
monarch/templates.py
monarch/utils.py
monarch.egg-info/PKG-INFO
monarch.egg-info/SOURCES.txt
monarch.egg-info/dependency_links.txt
monarch.egg-info/entry_points.txt
monarch.egg-info/requires.txt
monarch.egg-info/top_level.txt