Metadata-Version: 1.1
Name: monarch
Version: 0.1.7
Summary: The un-migration migration tool
Home-page: http://github.com/jtushman/monarch
Author: Jonathan Tushman
Author-email: jonathan@zefr.com
License: UNKNOWN
Platform: UNKNOWN
Classifier: Intended Audience :: Developers
Classifier: License :: OSI Approved :: MIT License
Classifier: Programming Language :: Python :: 2.7
Classifier: Programming Language :: Python :: 3
